tagfile.py
tagfile-0.1.0.dist-info/entry_points.txt
tagfile-0.1.0.dist-info/LICENSE
tagfile-0.1.0.dist-info/WHEEL
tagfile-0.1.0.dist-info/METADATA
tagfile-0.1.0.dist-info/RECORD
