Metadata-Version: 2.1
Name: tagfile
Version: 0.1.0
Summary: Search, index and tag your files and find duplicates
Keywords: tag,files,media,duplicate,duplicates,organize,checksum,locate,database,find,hash,filter,harddisk,space
Author-email: Benjamin Althues <benjamin@babab.nl>
Requires-Python: >=3.7
Classifier: Development Status :: 4 - Beta
Classifier: Environment :: Console
Classifier: Intended Audience :: Developers
Classifier: Intended Audience :: End Users/Desktop
Classifier: Intended Audience :: Information Technology
Classifier: Intended Audience :: System Administrators
Classifier: License :: OSI Approved :: BSD License
Classifier: Natural Language :: English
Classifier: Operating System :: OS Independent
Classifier: Programming Language :: Python :: 3
Classifier: Topic :: Database
Classifier: Topic :: Desktop Environment :: File Managers
Classifier: Topic :: Multimedia
Classifier: Topic :: Multimedia :: Graphics
Classifier: Topic :: Multimedia :: Sound/Audio
Classifier: Topic :: Multimedia :: Video
Classifier: Topic :: Scientific/Engineering :: Information Analysis
Classifier: Topic :: Software Development :: User Interfaces
Classifier: Topic :: System :: Filesystems
Classifier: Topic :: Utilities
Requires-Dist: ansicolors >=1.1.8,<2.0
Requires-Dist: peewee >=3.15.4,<4.0
Requires-Dist: pycommand >=0.4.0,<0.5
Requires-Dist: PyYAML >=6.0,<7.0
Project-URL: Home, https://github.com/babab/tagfile
